{
  "id": 10938,
  "title": "Innocent: Shoujo Memoria",
  "main_picture": {
    "medium": "https://cdn.myanimelist.net/images/anime/1099/104062.jpg",
    "large": "https://cdn.myanimelist.net/images/anime/1099/104062l.jpg"
  },
  "alternative_titles": {
    "synonyms": [
      "Innocent: Memories of a Girl"
    ],
    "en": "",
    "ja": "イノセント～少女メモリア～"
  },
  "start_date": "2011-07-05",
  "end_date": "2011-07-05",
  "synopsis": "Includes two short stories:\n\n1. A girl claims to be the reincarnation of an older man's deceased girlfriend in order to have sex with him.\n\n2. A girl decides to pretend to be asleep until her father comes back. Her brother, thinking she really is asleep, decides to take advantage of the opportunity and repeatedly have sex with her.",
  "mean": 5.89,
  "popularity": 9621,
  "num_list_users": 3594,
  "num_scoring_users": 1392,
  "nsfw": "gray",
  "created_at": "2011-07-10T17:53:30+00:00",
  "updated_at": "2019-11-02T17:30:31+00:00",
  "media_type": "ova",
  "status": "finished_airing",
  "genres": [
    {
      "id": 12,
      "name": "Hentai"
    }
  ],
  "num_episodes": 1,
  "start_season": {
    "year": 2011,
    "season": "summer"
  },
  "source": "manga",
  "average_episode_duration": 698,
  "rating": "rx",
  "studios": [
    {
      "id": 2315,
      "name": "Office No. 8"
    }
  ]
}