{
  "id": 1895,
  "title": "Ai wa Kagi no Kazu dake... Fuuzoku Mansion",
  "main_picture": {
    "medium": "https://cdn.myanimelist.net/images/anime/1200/112069.jpg",
    "large": "https://cdn.myanimelist.net/images/anime/1200/112069l.jpg"
  },
  "alternative_titles": {
    "synonyms": [
      "Ai ha Kagi no Kazu dake... Fuuzoku Mansion",
      "Love is the Number of Keys"
    ],
    "en": "Love is the Number of Keys",
    "ja": "愛は鍵の数だけ… 風俗マンション"
  },
  "start_date": "2002-05-25",
  "end_date": "2002-05-25",
  "synopsis": "Jun is on his own for the first time, as his father has gone overseas for a new job. He stays behind because of schooling and moves into an apartment complex as an assistant manager, only to discover that the place is a sex service apartment.",
  "mean": 6.21,
  "popularity": 8813,
  "num_list_users": 4622,
  "num_scoring_users": 1886,
  "nsfw": "gray",
  "created_at": "2007-01-27T22:58:55+00:00",
  "updated_at": "2022-03-23T03:52:41+00:00",
  "media_type": "ova",
  "status": "finished_airing",
  "genres": [
    {
      "id": 12,
      "name": "Hentai"
    }
  ],
  "num_episodes": 1,
  "start_season": {
    "year": 2002,
    "season": "spring"
  },
  "source": "original",
  "average_episode_duration": 1735,
  "rating": "rx",
  "studios": [
    {
      "id": 2390,
      "name": "Concept Films"
    }
  ]
}