{
  "id": 3098,
  "title": "Shutsugeki! Machine Robo Rescue",
  "main_picture": {
    "medium": "https://cdn.myanimelist.net/images/anime/8/28127.webp",
    "large": "https://cdn.myanimelist.net/images/anime/8/28127l.webp"
  },
  "alternative_titles": {
    "synonyms": [
      "Machine Robo Rescue",
      "Sortie!"
    ],
    "en": "",
    "ja": "出撃！マシンロボレスキュー"
  },
  "start_date": "2003-01-08",
  "end_date": "2004-01-03",
  "synopsis": "In the future, age is not a factor to determine whether someone can perform a certain task or not, but special talent and training. An organization, Machine Robo Rescue (MRR), was established for robots and children to become partner and rescue people from danger. Then 12 children with various abilities were selected and introduced as part of this program: Robo Rescue! \n\nMeet Oozora Taiyou, one of the children who were chosen as a part of MRR program. After being late on his first day of training, he went to perform a hot rescue with JETROBO. However, a mysterious Robot from mysterious organization, \"The Star\"(?), appeared before MRR team to interfere with the rescue. What are the motives of the mysterious organization? And what are their goals? \n\nLife as one of the children chosen as part of MRR has started for Oozora Taiyou. Bumpy and hard training is just ahead for MRR team in order to protect many people's life!\n\n(Source: AnimeNfo)",
  "mean": 6.87,
  "rank": 5137,
  "popularity": 11315,
  "num_list_users": 2764,
  "num_scoring_users": 1197,
  "nsfw": "white",
  "created_at": "2007-09-08T20:16:00+00:00",
  "updated_at": "2025-10-17T22:56:16+00:00",
  "media_type": "tv",
  "status": "finished_airing",
  "genres": [
    {
      "id": 18,
      "name": "Mecha"
    },
    {
      "id": 24,
      "name": "Sci-Fi"
    }
  ],
  "num_episodes": 53,
  "start_season": {
    "year": 2003,
    "season": "winter"
  },
  "broadcast": {
    "day_of_the_week": "wednesday",
    "start_time": "18:00"
  },
  "average_episode_duration": 1415,
  "rating": "pg",
  "studios": [
    {
      "id": 14,
      "name": "Sunrise"
    }
  ]
}