{
  "id": 32073,
  "title": "Otoshidama",
  "main_picture": {
    "medium": "https://cdn.myanimelist.net/images/anime/5/77109.jpg",
    "large": "https://cdn.myanimelist.net/images/anime/5/77109l.jpg"
  },
  "alternative_titles": {
    "synonyms": [
      "Minna no Uta"
    ],
    "en": "",
    "ja": "お年玉"
  },
  "start_date": "1997-12-02",
  "end_date": "1997-12-02",
  "synopsis": "A music video for the song \"Otoshidama\" by Hikari Ishida. Aired as part of NHK's Minna no Uta program.",
  "popularity": 19531,
  "num_list_users": 261,
  "num_scoring_users": 106,
  "nsfw": "white",
  "created_at": "2015-11-15T11:14:40+00:00",
  "updated_at": "2019-01-31T02:24:47+00:00",
  "media_type": "music",
  "status": "finished_airing",
  "genres": [
    {
      "id": 15,
      "name": "Kids"
    },
    {
      "id": 19,
      "name": "Music"
    }
  ],
  "num_episodes": 1,
  "start_season": {
    "year": 1997,
    "season": "fall"
  },
  "source": "original",
  "average_episode_duration": 140,
  "rating": "g",
  "studios": []
}