{
  "id": 37385,
  "title": "Tough Boy",
  "main_picture": {
    "medium": "https://cdn.myanimelist.net/images/anime/1569/90777.webp",
    "large": "https://cdn.myanimelist.net/images/anime/1569/90777l.webp"
  },
  "alternative_titles": {
    "synonyms": [
      "TOUGH BOY／MEG × the telephones"
    ],
    "en": "Tough Boy",
    "ja": "TOUGH BOY"
  },
  "start_date": "2012-04-22",
  "end_date": "2012-04-22",
  "synopsis": "Music video for the cover of \"Tough Boy\" by Meg and the telephones.",
  "mean": 4.87,
  "popularity": 18442,
  "num_list_users": 416,
  "num_scoring_users": 223,
  "nsfw": "white",
  "created_at": "2018-02-25T21:06:11+00:00",
  "updated_at": "2018-03-19T15:39:15+00:00",
  "media_type": "music",
  "status": "finished_airing",
  "genres": [
    {
      "id": 1,
      "name": "Action"
    },
    {
      "id": 19,
      "name": "Music"
    },
    {
      "id": 20,
      "name": "Parody"
    }
  ],
  "num_episodes": 1,
  "start_season": {
    "year": 2012,
    "season": "spring"
  },
  "source": "music",
  "average_episode_duration": 201,
  "rating": "g",
  "studios": []
}