{
  "id": 53502,
  "title": "Catch",
  "main_picture": {
    "medium": "https://cdn.myanimelist.net/images/anime/1614/130404.jpg",
    "large": "https://cdn.myanimelist.net/images/anime/1614/130404l.jpg"
  },
  "alternative_titles": {
    "synonyms": [],
    "en": "",
    "ja": "CATCH"
  },
  "start_date": "2016-04-14",
  "end_date": "2016-04-14",
  "synopsis": "Music video for the song CATCH by group_inou from their 4th album \"MAP\".",
  "popularity": 22909,
  "num_list_users": 140,
  "num_scoring_users": 72,
  "nsfw": "white",
  "created_at": "2022-11-03T04:22:19+00:00",
  "updated_at": "2022-12-20T12:18:49+00:00",
  "media_type": "music",
  "status": "finished_airing",
  "genres": [
    {
      "id": 1,
      "name": "Action"
    },
    {
      "id": 4,
      "name": "Comedy"
    },
    {
      "id": 19,
      "name": "Music"
    }
  ],
  "num_episodes": 1,
  "start_season": {
    "year": 2016,
    "season": "spring"
  },
  "source": "original",
  "average_episode_duration": 178,
  "rating": "pg_13",
  "studios": []
}