{
  "id": 57489,
  "title": "Fudanshi Shoukan: Isekai de Shinjuu ni Hameraremashita 6th Season",
  "main_picture": {
    "medium": "https://cdn.myanimelist.net/images/anime/1294/140365.webp",
    "large": "https://cdn.myanimelist.net/images/anime/1294/140365l.webp"
  },
  "alternative_titles": {
    "synonyms": [],
    "en": "",
    "ja": "腐男子召喚〜異世界で神獣にハメられました〜 6th"
  },
  "start_date": "2023-12-08",
  "end_date": "2023-12-22",
  "synopsis": "Sixth season of Fudanshi Shoukan: Isekai de Shinjuu ni Hameraremashita.",
  "mean": 5.68,
  "rank": 11919,
  "popularity": 17459,
  "num_list_users": 535,
  "num_scoring_users": 150,
  "nsfw": "gray",
  "created_at": "2023-12-08T12:34:15+00:00",
  "updated_at": "2024-03-29T14:49:08+00:00",
  "media_type": "ona",
  "status": "finished_airing",
  "genres": [
    {
      "id": 28,
      "name": "Boys Love"
    },
    {
      "id": 10,
      "name": "Fantasy"
    },
    {
      "id": 62,
      "name": "Isekai"
    }
  ],
  "num_episodes": 3,
  "start_season": {
    "year": 2023,
    "season": "fall"
  },
  "source": "web_manga",
  "average_episode_duration": 120,
  "rating": "pg_13",
  "studios": [
    {
      "id": 2071,
      "name": "AQUA ARIS"
    }
  ]
}