{
  "id": 59065,
  "title": "Pororo Gonglyong Ppyeoga Sal-anassda!",
  "main_picture": {
    "medium": "https://cdn.myanimelist.net/images/anime/1621/143563.jpg",
    "large": "https://cdn.myanimelist.net/images/anime/1621/143563l.jpg"
  },
  "alternative_titles": {
    "synonyms": [
      "Dino Skeletons Came Alive"
    ],
    "en": "Pororo Movie: Pororo's Night at the Dinosaur Museum",
    "ja": "뽀로로 공룡 뼈가 살아났다!"
  },
  "start_date": "2023-04-28",
  "end_date": "2023-04-28",
  "synopsis": "One early morning, Pororo and his friends visit the nature history museum. Suddenly, the museum starts to shake, and the exhibits begin to tumble down! TongTong's magic spell misfires, and all of the exhibits come to life. Can our friends set everything back as they are? Come along for a wild museum adventure with Pororo and his friends!\n\n(Source: Amazon Prime)",
  "rank": 18292,
  "popularity": 27378,
  "num_list_users": 54,
  "num_scoring_users": 9,
  "nsfw": "white",
  "created_at": "2024-06-13T05:55:28+00:00",
  "updated_at": "2024-06-13T05:55:28+00:00",
  "media_type": "ona",
  "status": "finished_airing",
  "genres": [
    {
      "id": 2,
      "name": "Adventure"
    },
    {
      "id": 51,
      "name": "Anthropomorphic"
    },
    {
      "id": 15,
      "name": "Kids"
    }
  ],
  "num_episodes": 1,
  "start_season": {
    "year": 2023,
    "season": "spring"
  },
  "source": "original",
  "average_episode_duration": 2040,
  "rating": "g",
  "studios": []
}