{
  "id": 6098,
  "title": "Sora no Manimani",
  "main_picture": {
    "medium": "https://cdn.myanimelist.net/images/anime/6/75491.webp",
    "large": "https://cdn.myanimelist.net/images/anime/6/75491l.webp"
  },
  "alternative_titles": {
    "synonyms": [
      "Chuu no Manimani"
    ],
    "en": "At The Mercy of The Sky",
    "ja": "宙のまにまに"
  },
  "start_date": "2009-07-07",
  "end_date": "2009-09-22",
  "synopsis": "Saku Ooyagi returns to his hometown after seven years and is soon reacquainted with his childhood friend, Mihoshi Akeno. The reunion is far from merry since the last memory they have of each other is of her falling off a tree and him saving her. In any case, Mihoshi is determined to improve their relationship and forces Saku to join the astronomy club she founded.",
  "mean": 7.05,
  "rank": 4026,
  "popularity": 3434,
  "num_list_users": 44630,
  "num_scoring_users": 17770,
  "nsfw": "white",
  "created_at": "2009-02-21T13:36:39+00:00",
  "updated_at": "2022-11-14T08:45:33+00:00",
  "media_type": "tv",
  "status": "finished_airing",
  "genres": [
    {
      "id": 4,
      "name": "Comedy"
    },
    {
      "id": 22,
      "name": "Romance"
    },
    {
      "id": 23,
      "name": "School"
    },
    {
      "id": 42,
      "name": "Seinen"
    }
  ],
  "num_episodes": 12,
  "start_season": {
    "year": 2009,
    "season": "summer"
  },
  "broadcast": {
    "day_of_the_week": "tuesday",
    "start_time": "10:30"
  },
  "source": "manga",
  "average_episode_duration": 1475,
  "rating": "pg_13",
  "studios": [
    {
      "id": 126,
      "name": "Studio Comet"
    }
  ]
}