{
  "id": 61416,
  "title": "Wo Jide",
  "main_picture": {
    "medium": "https://cdn.myanimelist.net/images/anime/1510/149136.jpg",
    "large": "https://cdn.myanimelist.net/images/anime/1510/149136l.jpg"
  },
  "alternative_titles": {
    "synonyms": [],
    "en": "Teen on Shuqian Street",
    "ja": "我记得"
  },
  "start_date": "2022-08-28",
  "end_date": "2022-08-28",
  "synopsis": "Music video for the song Wo Jide by Zhao Lei.",
  "popularity": 28815,
  "num_list_users": 74,
  "num_scoring_users": 34,
  "nsfw": "white",
  "created_at": "2025-04-07T13:16:30+00:00",
  "updated_at": "2025-04-07T13:16:30+00:00",
  "media_type": "music",
  "status": "finished_airing",
  "genres": [
    {
      "id": 19,
      "name": "Music"
    }
  ],
  "num_episodes": 1,
  "start_season": {
    "year": 2022,
    "season": "summer"
  },
  "source": "original",
  "average_episode_duration": 352,
  "rating": "g",
  "studios": []
}